solring/Solring.py
solring/__init__.py
solring-0.0.2.dist-info/LICENSE
solring-0.0.2.dist-info/METADATA
solring-0.0.2.dist-info/WHEEL
solring-0.0.2.dist-info/entry_points.txt
solring-0.0.2.dist-info/top_level.txt
solring-0.0.2.dist-info/RECORD
